{
	"pages": [{
		"path": "pages/home/home",
		"style": {
			"navigationBarTitleText": "首页",
			"enablePullDownRefresh": false,
			"h5": {
				"titleNView": false
			}
		}

	}, {
		"path": "pages/find/find",
		"style": {
			"navigationBarTitleText": "发现",
			"enablePullDownRefresh": true,
			"h5": {
				"titleNView": false
			}

		}

	}, {
		"path": "pages/kind/kind",
		"style": {
			"navigationBarTitleText": "分类",
			"enablePullDownRefresh": false,
			"h5": {
				"titleNView": false
			}

		}

	}, {
		"path": "pages/user/user",
		"style": {
			"navigationBarTitleText": "我的",
			"enablePullDownRefresh": false,
			"h5": {
				"titleNView": false
			}
		}

	}, {
		"path": "pages/user/login/login",
		"style": {
			"navigationBarTitleText": "",
			"enablePullDownRefresh": false
		}

	}, {
		"path": "pages/user/myinfo/myinfo",
		"style": {
			"navigationBarTitleText": "个人信息",
			"enablePullDownRefresh": false
		}

	}, {
		"path": "pages/user/register/register",
		"style": {
			"navigationBarTitleText": "注册",
			"enablePullDownRefresh": false
		}

	}],
	"subPackages": [{
			"root": "goodsubpkg",
			"pages": [{
				"path": "goodsList/goodsList",
				"style": {
					"navigationBarTitleText": "分类详情",
					"enablePullDownRefresh": true,
					"onReachBottomDistance": 150
				}
			}, {
				"path": "goodsDetail/goodsDetail",
				"style": {
					"navigationBarTitleText": "商品详情",
					"enablePullDownRefresh": false
				}

			}, {
				"path": "detailAB/detailAB",
				"style": {
					"navigationBarTitleText": "",
					"enablePullDownRefresh": false
				}

			}, {
				"path": "goodsCollected/goodsCollected",
				"style": {
					"navigationBarTitleText": "商品收藏",
					"enablePullDownRefresh": false
				}

			}]
		},
		{
			"root": "minesubpkg",
			"pages": [{
				"path": "cart/cart",
				"style": {
					"navigationBarTitleText": "购物车",
					"enablePullDownRefresh": false
				}

			}, {
				"path": "order/order",
				"style": {
					"navigationBarTitleText": "订单",
					"enablePullDownRefresh": false
				}

			}, {
				"path": "address/address",
				"style": {
					"navigationBarTitleText": "地址",
					"enablePullDownRefresh": false
				}

			}, {
				"path": "addAddress/addAddress",
				"style": {
					"navigationBarTitleText": "",
					"enablePullDownRefresh": false
				}

			}, {
				"path": "orderList/orderList",
				"style": {
					"navigationBarTitleText": "",
					"enablePullDownRefresh": false
				}

			}, {
				"path": "payment/payment",
				"style": {
					"navigationBarTitleText": "支付",
					"enablePullDownRefresh": false
				}

			}, {
				"path": "orderBack/orderBack",
				"style": {
					"navigationBarTitleText": "反馈",
					"enablePullDownRefresh": false
				}

			}, {
				"path": "findCollected/findCollected",
				"style": {
					"navigationBarTitleText": "文章收藏",
					"enablePullDownRefresh": false
				}

			}]
		}
	],
	"tabBar": {
		"color": "#7A7E83",
		"selectedColor": "#3cc51f",
		"borderStyle": "black",
		"backgroundColor": "#ffffff",
		"list": [{
				"pagePath": "pages/home/home",
				"iconPath": "static/images/icons/home.png",
				"selectedIconPath": "static/images/icons/home-active.png",
				"text": "首页"
			},
			{
				"pagePath": "pages/kind/kind",
				"iconPath": "static/images/icons/kind.png",
				"selectedIconPath": "static/images/icons/kind-active.png",
				"text": "分类"
			},
			{
				"pagePath": "pages/find/find",
				"iconPath": "static/images/icons/find.png",
				"selectedIconPath": "static/images/icons/find-active.png",
				"text": "发现"
			},
			{
				"pagePath": "pages/user/user",
				"iconPath": "static/images/icons/mine.png",
				"selectedIconPath": "static/images/icons/mine-active.png",
				"text": "我的"
			}
		]
	},
	"globalStyle": {
		"navigationBarTextStyle": "white",
		"navigationBarTitleText": "乐居",
		"navigationBarBackgroundColor": "#354e44",
		"backgroundColor": "#354e44",
		"app-plus": {
			"background": "#efeff4"
		}
	}
}
